CHANGES
COPYING
MANIFEST.in
README.rst
setup.cfg
setup.py
.idea/misc.xml
.idea/modules.xml
.idea/workspace.xml
.idea/inspectionProfiles/profiles_settings.xml
.tox/d110-py36/lib/python3.6/site-packages/Cryptodome/SelfTest/PublicKey/test_vectors/ECC/ecc_p256_private.pem
.tox/d110-py36/lib/python3.6/site-packages/Cryptodome/SelfTest/PublicKey/test_vectors/ECC/ecc_p256_private_enc_aes128.pem
.tox/d110-py36/lib/python3.6/site-packages/Cryptodome/SelfTest/PublicKey/test_vectors/ECC/ecc_p256_private_enc_aes192.pem
.tox/d110-py36/lib/python3.6/site-packages/Cryptodome/SelfTest/PublicKey/test_vectors/ECC/ecc_p256_private_enc_aes256_gcm.pem
.tox/d110-py36/lib/python3.6/site-packages/Cryptodome/SelfTest/PublicKey/test_vectors/ECC/ecc_p256_private_enc_des3.pem
.tox/d110-py36/lib/python3.6/site-packages/Cryptodome/SelfTest/PublicKey/test_vectors/ECC/ecc_p256_private_p8.pem
.tox/d110-py36/lib/python3.6/site-packages/Cryptodome/SelfTest/PublicKey/test_vectors/ECC/ecc_p256_private_p8_clear.pem
.tox/d110-py36/lib/python3.6/site-packages/Cryptodome/SelfTest/PublicKey/test_vectors/ECC/ecc_p256_public.pem
.tox/d110-py36/lib/python3.6/site-packages/Cryptodome/SelfTest/PublicKey/test_vectors/ECC/ecc_p256_public_compressed.pem
.tox/d110-py36/lib/python3.6/site-packages/Cryptodome/SelfTest/PublicKey/test_vectors/ECC/ecc_p256_x509.pem
.tox/d110-py36/lib/python3.6/site-packages/certifi/cacert.pem
.tox/d110-py36/lib/python3.6/site-packages/django/contrib/admin/templates/admin/404.html
.tox/d110-py36/lib/python3.6/site-packages/django/contrib/admin/templates/admin/500.html
.tox/d110-py36/lib/python3.6/site-packages/django/contrib/admin/templates/admin/actions.html
.tox/d110-py36/lib/python3.6/site-packages/django/contrib/admin/templates/admin/app_index.html
.tox/d110-py36/lib/python3.6/site-packages/django/contrib/admin/templates/admin/base.html
.tox/d110-py36/lib/python3.6/site-packages/django/contrib/admin/templates/admin/base_site.html
unicef_djangosaml2.egg-info/PKG-INFO
unicef_djangosaml2.egg-info/SOURCES.txt
unicef_djangosaml2.egg-info/dependency_links.txt
unicef_djangosaml2.egg-info/not-zip-safe
unicef_djangosaml2.egg-info/requires.txt
unicef_djangosaml2.egg-info/top_level.txt